MANIFEST.in
setup.py
cf_boot.egg-info/PKG-INFO
cf_boot.egg-info/SOURCES.txt
cf_boot.egg-info/dependency_links.txt
cf_boot.egg-info/entry_points.txt
cf_boot.egg-info/requires.txt
cf_boot.egg-info/top_level.txt
cfboot/VERSION
cfboot/__init__.py
cfboot/master/__init__.py
cfboot/master/bootstrap.py
cfboot/scripts/__init__.py
cfboot/scripts/cf-cups/README.html
cfboot/scripts/cf-cups/README.md
cfboot/scripts/cf-cups/README.org
cfboot/scripts/cf-cups/cf-cups.py
cfboot/scripts/cf-cups/sample.json
cfboot/scripts/cf-cups/test.json
cfboot/scripts/cf-push-app/README.html
cfboot/scripts/cf-push-app/README.md
cfboot/scripts/cf-push-app/README.org
cfboot/scripts/cf-push-app/cf-push-app.py
cfboot/scripts/cf-push-app/kibana-sample.json
cfboot/scripts/cf-push-app/pg-sample.json
cfboot/scripts/cf-push-app/postgress-bootstrapper.json
cfboot/scripts/create-acs-policy/README.org
cfboot/scripts/create-acs-policy/create-acs-policy.py
cfboot/scripts/create-acs-policy/sample.json
cfboot/scripts/create-service/README.html
cfboot/scripts/create-service/README.md
cfboot/scripts/create-service/README.org
cfboot/scripts/create-service/create-service.py
cfboot/scripts/create-service/sample.json
cfboot/scripts/create-service/uaa-sample.json
cfboot/scripts/create-uaa-clients/README.org
cfboot/scripts/create-uaa-clients/create-uaa-clients.py
cfboot/scripts/create-uaa-clients/sample_input.json
cfboot/scripts/create-unique-cf-home/README.html
cfboot/scripts/create-unique-cf-home/README.md
cfboot/scripts/create-unique-cf-home/README.org
cfboot/scripts/create-unique-cf-home/create-unique-cf-home.py
cfboot/scripts/extract-service-credentials/README.html
cfboot/scripts/extract-service-credentials/README.md
cfboot/scripts/extract-service-credentials/README.org
cfboot/scripts/extract-service-credentials/extract-service-credentials.py
cfboot/scripts/extract-service-credentials/sample-acs.json
cfboot/scripts/extract-service-credentials/sample-jdbc.json
cfboot/scripts/extract-service-credentials/sample-uaa.json
cfboot/scripts/printf/README.html
cfboot/scripts/printf/README.md
cfboot/scripts/printf/README.org
cfboot/scripts/printf/printf.py
cfboot/scripts/printf/test.json
