Metadata-Version: 1.1
Name: cf-boot
Version: 1.16.2
Summary: A declarative mechanism for
Home-page: https://github.build.ge.com/hubs/cf-bootstrapper
Author: Ernesto Alfonso, Weijie Lin
Author-email: ernesto.alfonsogonzalez@ge.com, weijie.lin@ge.com
License: BSD
Keywords: cloudfoundry cf bootstrap
Platform: UNKNOWN
Classifier: Development Status :: 4 - Beta
Classifier: Intended Audience :: Developers
Classifier: Topic :: Software Development :: Build Tools
Classifier: License :: OSI Approved :: BSD License
Classifier: Programming Language :: Python :: 2
Classifier: Programming Language :: Python :: 2.6
Classifier: Programming Language :: Python :: 2.7
